bl_hector/__init__.py
bl_hector/application/__init__.py
bl_hector/application/use_cases/__init__.py
bl_hector/application/use_cases/add_book.py
bl_hector/application/use_cases/display_book.py
bl_hector/application/use_cases/look_up_book.py
bl_hector/application/use_cases/search_books.py
bl_hector/application/use_cases/update_book.py
bl_hector/configuration/__init__.py
bl_hector/configuration/cli.py
bl_hector/configuration/wsgi.py
bl_hector/domain/__init__.py
bl_hector/domain/administration/__init__.py
bl_hector/domain/administration/entities.py
bl_hector/domain/administration/enumerations.py
bl_hector/domain/administration/repositories.py
bl_hector/domain/administration/services.py
bl_hector/domain/administration/value_objects.py
bl_hector/domain/collection_management/__init__.py
bl_hector/domain/collection_management/entities.py
bl_hector/domain/collection_management/errors.py
bl_hector/domain/collection_management/repositories.py
bl_hector/domain/collection_management/services.py
bl_hector/domain/collection_management/validators.py
bl_hector/domain/collection_management/value_objects.py
bl_hector/infrastructure/__init__.py
bl_hector/infrastructure/flask/__init__.py
bl_hector/infrastructure/flask/aliases/__init__.py
bl_hector/infrastructure/flask/auth/__init__.py
bl_hector/infrastructure/flask/books/__init__.py
bl_hector/infrastructure/flask/ip/__init__.py
bl_hector/infrastructure/flask/services.py
bl_hector/infrastructure/flask/static/css/bulma@0.9.4.min.css
bl_hector/infrastructure/flask/static/css/font-awesome@5.14.0.css
bl_hector/infrastructure/flask/static/css/hector.css
bl_hector/infrastructure/flask/static/favicon.svg
bl_hector/infrastructure/flask/static/img/placeholders/320x480.png
bl_hector/infrastructure/flask/static/js/htmx@1.9.6.min.js
bl_hector/infrastructure/flask/static/js/hyperscript@0.9.11.min.js
bl_hector/infrastructure/flask/static/js/simplewebauthn-browser@7.2.0.umd.min.js
bl_hector/infrastructure/flask/static/webfonts/fa-brands-400.ttf
bl_hector-0.4.6.dist-info/METADATA
bl_hector-0.4.6.dist-info/WHEEL
bl_hector-0.4.6.dist-info/entry_points.txt
bl_hector-0.4.6.dist-info/licenses/LICENSE
bl_hector-0.4.6.dist-info/RECORD
