Metadata-Version: 2.4
Name: bl_hector
Version: 0.4.6
Summary: A collection manager.
License: AGPL-3.0-or-later
License-File: LICENSE
Author: Tanguy Le Carrour
Author-email: tanguy@bioneland.org
Requires-Python: >=3.9,<4.0
Classifier: License :: OSI Approved :: GNU Affero General Public License v3 or later (AGPLv3+)
Classifier: Programming Language :: Python :: 3
Classifier: Programming Language :: Python :: 3.9
Classifier: Programming Language :: Python :: 3.10
Classifier: Programming Language :: Python :: 3.11
Classifier: Programming Language :: Python :: 3.12
Classifier: Programming Language :: Python :: 3.13
Classifier: Programming Language :: Python :: 3.14
Provides-Extra: totp
Provides-Extra: webauthn
Requires-Dist: Flask (>=2.3.2,<3.0.0)
Requires-Dist: SQLAlchemy (>=2.0.15,<3.0.0)
Requires-Dist: bl-seth (>=0.2.0,<0.3.0)
Requires-Dist: bl3d (>=1.0.0a1,<2.0.0)
Requires-Dist: fluent.runtime (>=0.4.0,<0.5.0)
Requires-Dist: isbnlib (>=3.10.14,<4.0.0)
Requires-Dist: jinja2-fragments (>=0.3.0,<0.4.0)
Requires-Dist: pyotp (>=2.8.0,<3.0.0) ; extra == "totp"
Requires-Dist: pypugjs (>=5.9.12,<6.0.0)
Requires-Dist: requests (>=2.31.0,<3.0.0)
Requires-Dist: typer (>=0.9.0,<0.10.0)
Requires-Dist: webauthn (>=1.8.1,<2.0.0) ; extra == "webauthn"
Project-URL: Repository, https://git.easter-eggs.org/bioneland/hector
